gimli/__init__.py
gimli/gimli.py
gimli-0.2.4.data/scripts/gimli
gimli-0.2.4.dist-info/LICENSE
gimli-0.2.4.dist-info/METADATA
gimli-0.2.4.dist-info/WHEEL
gimli-0.2.4.dist-info/top_level.txt
gimli-0.2.4.dist-info/RECORD
