Metadata-Version: 2.1
Name: gimli
Version: 0.2.4
Summary: Mines for system information. "AND MY AXE!" -Gimli
Home-page: https://github.com/second-breakfast/gimli
Author: Peregrin Took
Author-email: peregrin.took@example.com
License: MIT
Platform: UNKNOWN
